setup.cfg
setup.py
Cybernator/Paginator.py
Cybernator/Rolegator.py
Cybernator/__init__.py
Cybernator.egg-info/PKG-INFO
Cybernator.egg-info/SOURCES.txt
Cybernator.egg-info/dependency_links.txt
Cybernator.egg-info/not-zip-safe
Cybernator.egg-info/requires.txt
Cybernator.egg-info/top_level.txt