Metadata-Version: 1.0
Name: Cybernator
Version: 0.6.1
Summary: Paginator and Rolegator
Home-page: https://github.com/RuCybernetic/Cybernator
Author: UNKNOWN
Author-email: rucybernetic@yandex.ru
License: UNKNOWN
Platform: UNKNOWN
